{
    "AnswerPositions": [
        {
            "x": -3.7200000286102297,
            "y": 2.8399999141693117,
            "z": 0.0
        },
        {
            "x": -3.640000104904175,
            "y": 1.7740000486373902,
            "z": 0.0
        },
        {
            "x": -2.996999979019165,
            "y": 2.8949999809265138,
            "z": 0.0
        },
        {
            "x": -2.9639999866485597,
            "y": 2.252000093460083,
            "z": 0.0
        },
        {
            "x": -2.930000066757202,
            "y": 1.4769999980926514,
            "z": 0.0
        },
        {
            "x": -2.1449999809265138,
            "y": 2.8499999046325685,
            "z": 0.0
        },
        {
            "x": -2.312999963760376,
            "y": 2.1559998989105226,
            "z": 0.0
        },
        {
            "x": -2.23799991607666,
            "y": 1.3009999990463257,
            "z": 0.0
        },
        {
            "x": -1.371999979019165,
            "y": 2.630000114440918,
            "z": 0.0
        },
        {
            "x": -1.4500000476837159,
            "y": 1.593000054359436,
            "z": 0.0
        }
    ]
}